docanalysis/__init__.py
docanalysis/ami_sections.py
docanalysis/convert_file.py
docanalysis/docanalysis.py
docanalysis/entity_extraction.py
docanalysis/file_lib.py
docanalysis/get_html.py
docanalysis/glob_trail.py
docanalysis/gui.py
docanalysis/xml_lib.py
docanalysis-0.3.1.dist-info/licenses/LICENSE
docanalysis-0.3.1.dist-info/METADATA
docanalysis-0.3.1.dist-info/WHEEL
docanalysis-0.3.1.dist-info/entry_points.txt
docanalysis-0.3.1.dist-info/top_level.txt
docanalysis-0.3.1.dist-info/RECORD
