Metadata-Version: 2.4
Name: docanalysis
Version: 0.3.1
Summary: extract structured information from ethics paragraphs
Home-page: https://github.com/petermr/docanalysis
Author: Ayush Garg, Shweata N. Hegde
Author-email: ayush@science.org.in, shweata.hegde@gmail.com
License: Apache License
Keywords: research automation
Classifier: Development Status :: 4 - Beta
Classifier: Intended Audience :: Developers
Classifier: License :: OSI Approved :: Apache Software License
Classifier: Natural Language :: English
Classifier: Programming Language :: Python :: 3.4
Classifier: Programming Language :: Python :: 3.5
Classifier: Programming Language :: Python :: 3.6
Classifier: Programming Language :: Python :: 3.7
Classifier: Programming Language :: Python :: 3.8
Classifier: Programming Language :: Python :: 3.9
Classifier: Programming Language :: Python :: 3.10
License-File: LICENSE
Requires-Dist: abbreviations
Requires-Dist: beautifulsoup4==4.10.0
Requires-Dist: braceexpand==0.1.7
Requires-Dist: coloredlogs==15.0.1
Requires-Dist: ConfigArgParse==1.5.3
Requires-Dist: lxml>=4.8.0
Requires-Dist: nltk==3.6.7
Requires-Dist: pandas>=2.1.0
Requires-Dist: pygetpapers
Requires-Dist: pytest==6.2.5
Requires-Dist: setuptools==60.3.1
Requires-Dist: spacy<3.10,>=3.8
Requires-Dist: tkinterweb==3.10.7
Requires-Dist: tqdm==4.62.3
Dynamic: author
Dynamic: author-email
Dynamic: classifier
Dynamic: description
Dynamic: description-content-type
Dynamic: home-page
Dynamic: keywords
Dynamic: license
Dynamic: license-file
Dynamic: requires-dist
Dynamic: summary
